nodedge/__init__.py
nodedge/__main__.py
nodedge/action_palette.py
nodedge/animated_stack_widget.py
nodedge/application_styler.py
nodedge/connector.py
nodedge/edge.py
nodedge/edge_dragging.py
nodedge/edge_validators.py
nodedge/editor_widget.py
nodedge/editor_window.py
nodedge/flow_layout.py
nodedge/graphics_cut_line.py
nodedge/graphics_edge.py
nodedge/graphics_node.py
nodedge/graphics_node_content.py
nodedge/graphics_node_title_label.py
nodedge/graphics_scene.py
nodedge/graphics_socket.py
nodedge/graphics_splash_screen.py
nodedge/graphics_text_item.py
nodedge/graphics_view.py
nodedge/history_list_widget.py
nodedge/home_menu.py
nodedge/logger.py
nodedge/mdi_area.py
nodedge/mdi_widget.py
nodedge/mdi_window.py
nodedge/node.py
nodedge/node_tree_widget.py
nodedge/nodedge_app_window.py
nodedge/ntypes.py
nodedge/range_slider.py
nodedge/scene.py
nodedge/scene_clipboard.py
nodedge/scene_coder.py
nodedge/scene_history.py
nodedge/scene_item_detail_widget.py
nodedge/scene_items_table_widget.py
nodedge/scene_items_tree_widget.py
nodedge/scene_simulator.py
nodedge/serializable.py
nodedge/socket_type.py
nodedge/solver_dialog.py
nodedge/splash_screen.py
nodedge/utils.py
nodedge/blocks/__init__.py
nodedge/blocks/block.py
nodedge/blocks/block_config.py
nodedge/blocks/block_exception.py
nodedge/blocks/block_param.py
nodedge/blocks/graphics_block.py
nodedge/blocks/graphics_block_content.py
nodedge/blocks/graphics_input_block_content.py
nodedge/blocks/graphics_output_block_content.py
nodedge/blocks/op_node.py
nodedge/blocks/autogen/__init__.py
nodedge/blocks/autogen/advanced_maths/__init__.py
nodedge/blocks/autogen/advanced_maths/arccos_block.py
nodedge/blocks/autogen/advanced_maths/arccosh_block.py
nodedge/blocks/autogen/advanced_maths/arcsin_block.py
nodedge/blocks/autogen/advanced_maths/arcsinh_block.py
nodedge/blocks/autogen/advanced_maths/arctan2_block.py
nodedge/blocks/autogen/advanced_maths/arctan_block.py
nodedge/blocks/autogen/advanced_maths/arctanh_block.py
nodedge-0.5.1.dist-info/AUTHORS.rst
nodedge-0.5.1.dist-info/LICENSE
nodedge-0.5.1.dist-info/METADATA
nodedge-0.5.1.dist-info/WHEEL
nodedge-0.5.1.dist-info/entry_points.txt
nodedge-0.5.1.dist-info/top_level.txt
nodedge-0.5.1.dist-info/RECORD
