Metadata-Version: 2.1
Name: nodedge
Version: 0.5.1
Summary: Graphical editor for physical modeling and simulation.
Home-page: https://www.nodedge.io
Author: Anthony De Bortoli
Author-email: anthony.debortoli@nodedge.io
License: MIT
Project-URL: Website, https://nodedge.io
Project-URL: Documentation, https://nodedge.readthedocs.io/en/latest/
Project-URL: Source, https://github.com/nodedge/nodedge
Project-URL: Tracker, https://github.com/nodedge/nodedge/issues
Project-URL: Donate, https://github.com/sponsors/nodedge
Keywords: nodedge,editor,graphical-programming,simulation,physical-modeling,control-systems,dynamic-systems,python3,qt5,pyside6,platform-indenpendent,windows,linux,macos
Platform: Windows
Platform: Linux
Platform: Mac OS-X
Platform: Unix
Classifier: Development Status :: 2 - Pre-Alpha
Classifier: Intended Audience :: Developers
Classifier: License :: OSI Approved :: MIT License
Classifier: Natural Language :: English
Classifier: Programming Language :: Python :: 3.10
Requires-Python: >=3.9
License-File: LICENSE
License-File: AUTHORS.rst
Requires-Dist: asammdf ==7.3.18
Requires-Dist: coloredlogs ==15.0.1
Requires-Dist: npTDMS ==1.7.1
Requires-Dist: numpy ==1.26.2
Requires-Dist: pandas ==2.1.4
Requires-Dist: pyqtconsole ==1.2.3
Requires-Dist: pyqtgraph ==0.13.3
Requires-Dist: PySide6 ==6.6.1
Requires-Dist: PyYAML ==6.0.1
Requires-Dist: scipy ==1.11.4
Requires-Dist: tables ==3.9.2
Requires-Dist: types-PyYAML ==6.0.12.12
